core/__init__.py
core/actions.py
core/audit.py
core/db.py
core/errors.py
core/idempotency.py
core/migrations.py
core/models.py
core/observability.py
core/outbox.py
core/query_params.py
core/repository.py
core/schema_api.py
core/site_resolver.py
core/uow.py
core/versions.py
fa_service_core-0.2.0.dist-info/METADATA
fa_service_core-0.2.0.dist-info/WHEEL
fa_service_core-0.2.0.dist-info/RECORD
