Metadata-Version: 2.4
Name: fa-service-core
Version: 0.2.0
Summary: FastAPI microservices core library for CMS with multi-tenancy, RLS, and async SQLAlchemy
Author-email: Developer <dev@example.com>
License: MIT
Keywords: cms,fastapi,microservices,multi-tenant,rls,sqlalchemy
Classifier: Development Status :: 3 - Alpha
Classifier: Framework :: FastAPI
Classifier: Intended Audience :: Developers
Classifier: License :: OSI Approved :: MIT License
Classifier: Programming Language :: Python :: 3
Classifier: Programming Language :: Python :: 3.13
Classifier: Topic :: Internet :: WWW/HTTP :: HTTP Servers
Classifier: Topic :: Software Development :: Libraries :: Python Modules
Requires-Python: >=3.13
Requires-Dist: alembic==1.16.5
Requires-Dist: asyncio-compat==0.1.2
Requires-Dist: asyncpg==0.29.0
Requires-Dist: fastapi==0.117.1
Requires-Dist: httpx==0.28.1
Requires-Dist: jsonpatch==1.33
Requires-Dist: pydantic==2.10.2
Requires-Dist: python-multipart==0.0.12
Requires-Dist: redis==5.2.0
Requires-Dist: sqlalchemy[asyncio]==2.0.36
Requires-Dist: uvicorn[standard]==0.32.0
Provides-Extra: dev
Requires-Dist: black==24.10.0; extra == 'dev'
Requires-Dist: isort==5.13.2; extra == 'dev'
Requires-Dist: mypy==1.13.0; extra == 'dev'
Requires-Dist: pre-commit==4.0.1; extra == 'dev'
Requires-Dist: pytest-asyncio==0.24.0; extra == 'dev'
Requires-Dist: pytest-cov==6.0.0; extra == 'dev'
Requires-Dist: pytest==8.3.3; extra == 'dev'
Requires-Dist: ruff==0.7.4; extra == 'dev'
